miminions/__init__.py
miminions/main.py
miminions/core/__init__.py
miminions-0.1.0.dist-info/licenses/LICENSE
miminions-0.1.0.dist-info/METADATA
miminions-0.1.0.dist-info/WHEEL
miminions-0.1.0.dist-info/top_level.txt
miminions-0.1.0.dist-info/RECORD
