Metadata-Version: 2.4
Name: miminions
Version: 0.1.0
Summary: MiMinions - A Python package for managing and interacting with AI assistants
Home-page: https://github.com/yourusername/miminions
Author: Your Name
Author-email: "MiMinions.ai" <support@miminions.ai>
License: MIT License
Project-URL: Homepage, https://github.com/miminions/miminions
Project-URL: Repository, https://github.com/miminions/miminions.git
Keywords: ai,assistant,automation,productivity
Classifier: Development Status :: 3 - Alpha
Classifier: Intended Audience :: Developers
Classifier: License :: OSI Approved :: Mozilla Public License 2.0 (MPL 2.0)
Classifier: Programming Language :: Python :: 3
Classifier: Programming Language :: Python :: 3.8
Classifier: Programming Language :: Python :: 3.9
Classifier: Programming Language :: Python :: 3.10
Classifier: Programming Language :: Python :: 3.11
Requires-Python: >=3.7
License-File: LICENSE
Dynamic: author
Dynamic: home-page
Dynamic: license-file
Dynamic: requires-python
